tensorflowutil/__init__.py
tensorflowutil/main.py
tensorflowutil/version.py
tensorflowutil-0.1.7.dist-info/LICENSE
tensorflowutil-0.1.7.dist-info/METADATA
tensorflowutil-0.1.7.dist-info/WHEEL
tensorflowutil-0.1.7.dist-info/entry_points.txt
tensorflowutil-0.1.7.dist-info/top_level.txt
tensorflowutil-0.1.7.dist-info/RECORD
