Metadata-Version: 2.1
Name: tensorflowutil
Version: 0.1.7
Summary: Collection of some useful tensorflow util functions.
Home-page: https://github.com/accssharma/tensorflowutil
Author: Ashish Sharma
Author-email: accssharma@gmail.com
License: MIT
Platform: UNKNOWN
Classifier: Development Status :: 4 - Beta
Classifier: Intended Audience :: Developers
Classifier: License :: OSI Approved :: MIT License
Classifier: Operating System :: OS Independent
Classifier: Programming Language :: Python
Classifier: Programming Language :: Python :: 3.6
Classifier: Programming Language :: Python :: 3.7
Requires-Dist: tensorflow (==1.13.1)
